{"servers":[
  {
    "name": "tikv1",
    "privateip": "localhost",
    "datadir": "/data1",
    "partition": "/dev/sdc",
    "file_system": "ext4",
    "swapfile": "/data1/swapfile",
    "swapbs": 1024,
    "swapcount": 25165824,
    "cpu": 1,
    "process": "tikv-server",
    "deploy_dir": "/data1/tidb-deploy",
    "data_dir": "/data1/tidb-data",
    "port_offset": 0
  },
  {
    "name": "tikv2",
    "privateip": "localhost",
    "datadir": "/data2",
    "partition": "/dev/sdc",
    "file_system": "ext4",
    "swapfile": "/data2/swapfile",
    "swapbs": 1024,
    "swapcount": 25165824,
    "cpu": 2,
    "process": "tikv-server",
    "deploy_dir": "/data2/tidb-deploy",
    "data_dir": "/data2/tidb-data",
    "port_offset": 1
  },
  {
    "name": "tikv3",
    "privateip": "localhost",
    "datadir": "/data3",
    "partition": "/dev/sdc",
    "file_system": "ext4",
    "swapfile": "/data3/swapfile",
    "swapbs": 1024,
    "swapcount": 25165824,
    "cpu": 3,
    "process": "tikv-server",
    "deploy_dir": "/data3/tidb-deploy",
    "data_dir": "/data3/tidb-data",
    "port_offset": 2
  }
  ],
  "pd":{
    "name": "pd",
    "privateip": "localhost",
    "datadir": "/data0",
    "partition": "/dev/sdc",
    "file_system": "ext4",
    "swapfile": "/data0/swapfile",
    "swapbs": 1024,
    "swapcount": 25165824,
    "cpu": 0,
    "deploy_dir": "/data0/tidb-deploy",
    "data_dir": "/data0/tidb-data",
    "tiup": "~/.tiup/bin/tiup"
  },
  "client": {
      "name": "client",
      "privateip": "localhost",
      "ycsb": "/home/tidb/go-ycsb/bin/go-ycsb"
  }
}